[
{"model": "کی ام سی، J7", "price": "1,540,000,000"},
{"model": "کیا، اپتیما", "price": "2,300,000,000"},
{"model": "جک، جی 4", "price": null},
{"model": "فونیکس، تیگو 8 پرو مکس", "price": null},
{"model": "تویوتا، کرولا", "price": null},
{"model": "لکسوس، NX هیبرید", "price": null},
{"model": "فونیکس، FX", "price": null},
{"model": "کی ام سی، A5", "price": "1,560,000,000"},
{"model": "فونیکس، تیگو 8 پرو مکس", "price": null},
{"model": "پژو، 206", "price": "309,000,000"},
{"model": "کی ام سی، eJ7", "price": null},
{"model": "کی ام سی، K7", "price": "1,550,000,000"},
{"model": "جک، S3", "price": null},
{"model": "کی ام سی، J7", "price": null},
{"model": "تویوتا، کرولا", "price": "2,680,000,000"},
{"model": "دنا، پلاس EF7", "price": "880,000,000"},
{"model": "فونیکس، FX", "price": null},
{"model": "کوییک، SR", "price": null},
{"model": "زامیاد، وانت نیسان", "price": null},
{"model": "هایما، S7", "price": null},
{"model": "ام وی ام، X55 PRO", "price": null},
{"model": "هیوندای، سانتافه", "price": null},
{"model": "تارا، دنده ای V1", "price": null},
{"model": "پژو، 207", "price": "885,000,000"},
{"model": "فونیکس، آریزو 8", "price": null},
{"model": "هیوندای، النترا", "price": null},
{"model": "ام وی ام، X33 کراس", "price": "950,600,000"},
{"model": "ام وی ام، X33 کراس", "price": "950,000,000"},
{"model": "هیوندای، توسان", "price": null},
{"model": "ام وی ام، X22 PRO", "price": "858,800,000"},
{"model": "نیسان، رونیز", "price": "1,280,000,000"},
{"model": "پژو، روآ", "price": "110,000,000"},
{"model": "هیوندای، اکسنت (مونتاژ)", "price": "1,480,000,000"},
{"model": "فونیکس، آریزو 6 جی تی", "price": "1,800,000,000"},
{"model": "تویوتا، پرادو دو در", "price": null},
{"model": "پژو، پارس", "price": "580,000,000"},
{"model": "ام وی ام، 315هاچ بک", "price": "620,000,000"},
{"model": "کی ام سی، eJ7", "price": null},
{"model": "ام وی ام، 530", "price": "355,000,000"},
{"model": "نیسان، سانی", "price": null},
{"model": "کوییک، R پلاس", "price": null},
{"model": "کی ام سی، J7", "price": null},
{"model": "پراید، 151", "price": null},
{"model": "پژو، 2008", "price": "1,700,000,000"},
{"model": "فونیکس، تیگو 7 پرو", "price": null},
{"model": "لاماری، ایما", "price": null},
{"model": "تویوتا، C-HR هیبرید", "price": null},
{"model": "نیسان، ایکس تریل", "price": "3,800,000,000"},
{"model": "فونیکس، FX", "price": null},
{"model": "نیسان، ماکسیما", "price": "1,490,000,000"},
{"model": "چری، آریزو 5T اسپرت FL", "price": "1,350,000,000"},
{"model": "فونیکس، FX", "price": null},
{"model": "لاماری، ایما HEV", "price": "2,280,000,000"},
{"model": "هایما، 8S", "price": null},
{"model": "پژو، 405", "price": null},
{"model": "پژو، 206", "price": "395,000,000"},
{"model": "دیگنیتی، پرستیژ", "price": "2,275,000,000"},
{"model": "کی ام سی، T9", "price": "2,330,000,000"},
{"model": "چری، آریزو 5T", "price": "1,050,000,000"},
{"model": "تارا، دنده ای V1 پلاس", "price": "750,000,000"},
{"model": "چانگان، CS 35 پلاس", "price": "1,500,000,000"},
{"model": "فولکس، تیگوان", "price": "4,650,000,000"},
{"model": "تویوتا، پرادو چهار در", "price": "7,850,000,000"},
{"model": "فونیکس، تیگو 7 پرو", "price": null},
{"model": "تارا، اتوماتیک V4", "price": "985,000,000"},
{"model": "لکسوس، NX هیبرید", "price": "5,600,000,000"},
{"model": "پژو، 207", "price": "710,000,000"},
{"model": "آلفارومئو، جولیتا", "price": null},
{"model": "فیدلیتی، پرایم", "price": "1,536,000,000"},
{"model": "بنز، کلاس C", "price": null},
{"model": "فونیکس، تیگو 8 پرو مکس", "price": null},
{"model": "بنز، کلاس E", "price": null},
{"model": "تارا، اتوماتیک V4", "price": "925,000,000"},
{"model": "ساینا، S", "price": null},
{"model": "پژو، 206", "price": "435,000,000"},
{"model": "شاهین، G دنده ای", "price": null},
{"model": "زوتی، DL5", "price": "1,027,000,000"},
{"model": "ام وی ام، X55 PRO", "price": "1,340,000,000"},
{"model": "تارا، دنده ای V1", "price": null},
{"model": "پروتون، جن تو", "price": "315,000,000"},
{"model": "تارا، اتوماتیک V4", "price": null},
{"model": "پژو، 207", "price": "700,000,000"},
{"model": "رنو، پارس تندر", "price": null},
{"model": "دنا، پلاس EF7", "price": null},
{"model": "ولوو، XC60", "price": "2,700,000,000"},
{"model": "پژو، پارس", "price": "700,000,000"},
{"model": "شاهین، G اتومات", "price": "765,000,000"},
{"model": "هایما، S7", "price": "1,560,000,000"},
{"model": "دیگنیتی، پرستیژ", "price": "2,210,000,000"},
{"model": "لیفان، X60", "price": "600,000,000"},
{"model": "فونیکس، تیگو 7 پرو", "price": null},
{"model": "ب ام و، سری 4 کروک", "price": null},
{"model": "کی ام سی، T8", "price": null},
{"model": "پژو، 206", "price": "380,000,000"},
{"model": "تویوتا، لوین", "price": "2,590,000,000"},
{"model": "پژو، 207", "price": null},
{"model": "میتسوبیشی، اوتلندر", "price": null},
{"model": "رنو، داستر", "price": null},
{"model": "تویوتا، کمری", "price": null},
{"model": "هیوندای، سانتافه", "price": null},
{"model": "ب ام و، X3", "price": null},
{"model": "مزدا، 3 نیو صندوق دار", "price": null},
{"model": "سهند، S دنده ای", "price": "510,000,000"},
{"model": "بنز، کلاس C", "price": "6,000,000,000"},
{"model": "پژو، 206", "price": "345,000,000"},
{"model": "فولکس، تیگوان", "price": null},
{"model": "فولکس، تیگوان", "price": null},
{"model": "دنا، پلاس EF7P", "price": "990,000,000"},
{"model": "کیا، سورنتو", "price": "5,530,000,000"},
{"model": "ولوو، XC90", "price": "13,500,000,000"},
{"model": "هایما، S5", "price": "1,090,000,000"},
{"model": "تویوتا، لندکروز چهار در", "price": "19,000,000,000"},
{"model": "تویوتا، کرولا", "price": "1,900,000,000"},
{"model": "بنز، کلاس S", "price": "8,500,000,000"},
{"model": "جک، جی 4", "price": null},
{"model": "شاهین، G اتومات", "price": "785,000,000"},
{"model": "فونیکس، تیگو 7 پرو هیبرید", "price": "1,976,900,000"},
{"model": "سمند، سورن", "price": "650,000,000"},
{"model": "پژو، پارس", "price": "43,000,000"},
{"model": "ام وی ام، X55 PRO", "price": "1,471,000,000"},
{"model": "فونیکس، تیگو 8 پرو", "price": null},
{"model": "تویوتا، C-HR هیبرید", "price": "4,550,000,000"},
{"model": "فولکس، گوناگون", "price": "1,900,000,000"},
{"model": "فونیکس، تیگو 8 پرو مکس", "price": null},
{"model": "جک، S5", "price": "1,020,000,000"},
{"model": "سیتروئن، زانتیا", "price": "325,000,000"},
{"model": "دیگنیتی، پرایم", "price": null},
{"model": "هیوندای، النترا", "price": null},
{"model": "چانگان، CS 35 پلاس", "price": null},
{"model": "فونیکس، آریزو 6 پرو", "price": null},
{"model": "ام وی ام، X55 PRO", "price": null},
{"model": "پژو، 405", "price": "640,000,000"},
{"model": "هیوندای، توسان", "price": null},
{"model": "کی ام سی، K7", "price": null},
{"model": "کی ام سی، J7", "price": null},
{"model": "جک، جی 4", "price": "755,000,000"},
{"model": "پژو، پارس", "price": "615,000,000"},
{"model": "پژو، 2008", "price": "1,650,000,000"},
{"model": "جک، S3", "price": null},
{"model": "پراید، 141", "price": "165,000,000"},
{"model": "تارا، دنده ای V1", "price": null},
{"model": "فونیکس، آریزو 6 جی تی", "price": null},
{"model": "کی ام سی، T9", "price": null},
{"model": "تویوتا، لوین هیبرید", "price": null},
{"model": "دانگ فنگ، شاین مکس", "price": null},
{"model": "چانگان، CS 55 پلاس", "price": null},
{"model": "تویوتا، کرولا", "price": null},
{"model": "نیسان، سیلفی e-POWER", "price": null},
{"model": "کیا، K5", "price": null},
{"model": "کی ام سی، T8", "price": null},
{"model": "فونیکس، تیگو 8 پرو مکس", "price": null},
{"model": "فونیکس، FX", "price": null},
{"model": "اطلس، G", "price": null},
{"model": "ام وی ام، X55 PRO", "price": null},
{"model": "فونیکس، تیگو 7 پرو", "price": null},
{"model": "فونیکس، تیگو 7 پرو", "price": null},
{"model": "هونگچی، H5", "price": null},
{"model": "هایما، S7", "price": null},
{"model": "هایما، S5", "price": null},
{"model": "فیدلیتی، پرایم", "price": null},
{"model": "دیگنیتی، پرستیژ", "price": null},
{"model": "پژو، 207", "price": null},
{"model": "پژو، 207", "price": null},
{"model": "هایما، S7", "price": null},
{"model": "دیگنیتی، پرستیژ", "price": null},
{"model": "دیگنیتی، پرایم", "price": null},
{"model": "دیگنیتی، پرستیژ", "price": null},
{"model": "هایما، 8S", "price": null},
{"model": "تارا، اتوماتیک V2", "price": null},
{"model": "کی ام سی، J7", "price": null},
{"model": "هایما، S5", "price": null},
{"model": "پژو، 207", "price": null},
{"model": "هایما، 7X", "price": null},
{"model": "کی ام سی، J7", "price": null},
{"model": "دیگنیتی، پرایم", "price": null},
{"model": "هایما، 8S", "price": null},
{"model": "لاماری، ایما", "price": null},
{"model": "جک، جی 4", "price": null},
{"model": "دیگنیتی، پرایم", "price": null},
{"model": "ساینا، S", "price": null},
{"model": "فیدلیتی، پرایم", "price": null},
{"model": "فیدلیتی، پرایم", "price": null},
{"model": "دنا، پلاس EF7", "price": null},
{"model": "لاماری، ایما", "price": null},
{"model": "فیدلیتی، پرایم", "price": null},
{"model": "پژو، 207", "price": null},
{"model": "لاماری، ایما", "price": null},
{"model": "ریسپکت، پرایم", "price": null},
{"model": "دنا، پلاس EF7", "price": null},
{"model": "پژو، 207", "price": null},
{"model": "پژو، 207", "price": null},
{"model": "دیگنیتی، پرستیژ", "price": null},
{"model": "پژو، 207", "price": null},
{"model": "تویوتا، کرولا", "price": null},
{"model": "ریسپکت، پرایم", "price": null},
{"model": "پژو، 207", "price": null},
{"model": "چانگان، CS 35 پلاس", "price": null},
{"model": "بی ای سی، X3 PRO", "price": null},
{"model": "جک، جی 4", "price": null},
{"model": "بی ای سی، X3 PRO", "price": null},
{"model": "کی ام سی، T9", "price": null},
{"model": "کی ام سی، T8", "price": null},
{"model": "پژو، 207", "price": "680,000,000"},
{"model": "سوزوکی، سیاز", "price": null},
{"model": "دانگ فنگ، شاین مکس", "price": null},
{"model": "سوزوکی، بالنو", "price": null},
{"model": "جک، جی 4", "price": null},
{"model": "یوآز، پاتریوت", "price": "1,450,000,000"},
{"model": "پژو، 207", "price": "860,000,000"},
{"model": "تویوتا، پرادو دو در", "price": null}
]